spiderlab/__init__.py
spiderlab/main.py
spiderlab-0.0.1.dist-info/LICENSE
spiderlab-0.0.1.dist-info/METADATA
spiderlab-0.0.1.dist-info/WHEEL
spiderlab-0.0.1.dist-info/top_level.txt
spiderlab-0.0.1.dist-info/RECORD
